[["onChat", {"onChat": "pic1:{grass,21.07,oak_leaves,28.59,oak_leaves,28.58,grass_block,16.90,grass,18.83,grass,17.68,grass_block,16.35,grass_block,16.10,grass_block,20.66,grass_block,19.97,grass_block,19.31,grass_block,18.68,grass_block,18.08,grass_block,15.71,oak_log,14.80,sand,22.24,grass_block,15.64,grass_block,15.18,oak_leaves,20.16,grass,13.86,oak_leaves,19.50,oak_log,20.24,oak_log,13.92,oak_log,20.32,oak_log,14.03,oak_leaves,18.86,grass,10.84,grass,13.60,oak_leaves,12.61,oak_leaves,12.04,oak_leaves,11.53,grass,21.37,grass,11.52,grass,10.33,grass,9.83,grass_block,10.74,oak_leaves,7.96,grass_block,15.06,grass,9.32,grass_block,8.66,grass,18.76,oak_leaves,10.49,oak_leaves,7.34,grass_block,15.57,oak_log,11.07,grass,10.23,grass_block,6.68,grass_block,6.21,grass_block,5.88,grass_block,5.71,oak_log,11.12,grass,6.75,oak_log,11.25,oak_leaves,9.88,grass_block,15.24,grass,17.18,oak_leaves,9.34,grass_block,8.42,grass_block,15.93,grass,5.82,grass,3.98,oak_leaves,9.74,grass_block,8.97,dirt,15.73,oak_log,15.76,oak_log,15.86,grass_block,8.72,grass_block,3.18,grass_block,2.47,grass_block,2.02,grass_block,15.59,birch_leaves,12.96,grass_block,2.78,grass_block,1.93,grass_block,1.31,grass_block,16.51,birch_leaves,12.87,grass_block,2.71,birch_log,14.50,crafting_table,0.59,birch_log,14.54,birch_log,14.64,birch_leaves,12.86,oak_leaves,9.02,grass_block,3.00,oak_leaves,8.83,oak_leaves,8.18,grass,20.63,grass,16.66,birch_leaves,9.98,birch_log,11.97,birch_log,12.01,birch_leaves,10.26,birch_leaves,10.50,oak_leaves,4.72,oak_leaves,20.97,birch_leaves,10.62,birch_leaves,10.86,oak_log,5.34,oak_log,5.43,oak_leaves,12.41,oak_leaves,12.61,oak_log,14.48,grass,11.99,oak_log,14.52,oak_leaves,12.95,oak_leaves,13.14,grass,13.39,oak_leaves,9.97,oak_leaves,9.45,oak_leaves,9.02,oak_leaves,8.68,oak_leaves,10.02,oak_leaves,9.51,oak_leaves,9.08,oak_leaves,8.74,oak_leaves,8.51,oak_leaves,13.54,oak_leaves,13.73,oak_leaves,9.43,oak_leaves,13.34,oak_leaves,13.45,oak_leaves,12.77,birch_leaves,12.13,birch_leaves,11.53,birch_leaves,11.00,oak_leaves,10.15,oak_leaves,9.64,birch_leaves,12.33,birch_leaves,11.75,birch_leaves,11.23,birch_leaves,10.77,oak_leaves,13.40,oak_leaves,10.80,oak_leaves,15.02,oak_leaves,14.34,oak_log,15.44,grass,19.80,grass,25.00,grass,24.02,oak_log,22.51},yaw=0.00", "voxels": ["grass_block", "crafting_table", "oak_log"], "status": {"health": 20, "food": 20, "saturation": 5, "oxygen": 317, "position": {"x": 5270.685021454552, "y": 73, "z": -4301.5}, "velocity": {"x": 0, "y": -0.0784000015258789, "z": 0}, "yaw": -1.5707963267946035, "pitch": -1.1047934165123419, "onGround": true, "equipment": [null, null, null, null, null, null], "name": "bot", "isInWater": false, "isInLava": false, "isCollidedHorizontally": false, "isCollidedVertically": true, "biome": "forest", "entities": {"cat": 24.369180036926114}, "timeOfDay": "day", "inventoryUsed": 1, "elapsedTime": 20}, "inventory": {"oak_log": 20}, "nearbyChests": {}, "blockRecords": ["dirt", "grass_block", "birch_log", "grass", "birch_leaves", "stone", "sand", "oak_log", "oak_leaves", "oak_planks", "crafting_table"]}], ["onChat", {"onChat": "pic2:{grass,21.07,oak_leaves,28.59,oak_leaves,28.58,oak_leaves,18.75,grass_block,16.90,grass,18.83,grass,17.68,grass_block,16.35,grass_block,16.10,oak_leaves,23.64,grass_block,20.66,grass_block,19.97,grass_block,19.31,grass_block,18.68,grass_block,18.08,grass_block,15.71,oak_log,14.80,oak_leaves,23.03,sand,22.24,grass_block,15.64,grass_block,15.18,oak_leaves,20.16,grass,13.86,oak_leaves,19.50,oak_log,20.24,oak_log,13.92,oak_log,20.32,oak_log,14.03,oak_leaves,18.86,grass,10.84,oak_leaves,19.16,oak_leaves,18.28,grass,13.60,oak_leaves,18.30,oak_leaves,12.61,oak_leaves,12.04,oak_leaves,11.53,oak_leaves,19.56,oak_leaves,17.77,grass,21.37,grass,11.52,grass,10.33,grass,9.83,oak_log,8.87,oak_leaves,17.80,grass_block,10.74,oak_log,8.91,oak_leaves,7.96,grass_block,15.06,grass,9.32,grass_block,8.66,grass,18.76,oak_leaves,7.21,oak_leaves,7.00,oak_leaves,7.14,oak_leaves,7.41,oak_leaves,10.49,oak_leaves,7.34,oak_leaves,7.34,oak_leaves,7.48,oak_leaves,7.74,oak_leaves,8.12,oak_leaves,8.60,oak_leaves,9.16,grass_block,15.57,oak_log,11.07,grass,10.23,grass_block,6.68,grass_block,6.21,grass_block,5.88,grass_block,5.71,grass_block,5.71,grass_block,5.88,oak_log,11.12,grass,6.75,grass,5.79,oak_leaves,6.75,oak_leaves,7.32,oak_log,11.25,oak_leaves,6.97,oak_leaves,7.52,oak_leaves,9.88,oak_leaves,9.14,grass_block,15.24,grass,17.18,oak_leaves,8.26,oak_leaves,9.34,oak_leaves,8.56,grass_block,8.42,grass_block,15.93,grass,5.82,grass,3.98,oak_log,9.26,oak_log,9.32,oak_leaves,7.73,oak_leaves,9.74,oak_leaves,8.05,grass_block,8.97,dirt,15.73,oak_log,15.76,oak_log,15.86,oak_leaves,7.31,oak_leaves,7.65,grass_block,8.72,grass_block,3.18,grass_block,2.47,grass_block,2.02,grass_block,2.02,grass_block,2.47,grass_block,15.59,birch_leaves,12.96,grass_block,2.78,grass_block,1.93,grass_block,1.31,grass_block,1.31,grass_block,1.93,grass_block,16.51,oak_log,2.59,oak_log,2.78,oak_log,3.27,birch_leaves,12.87},yaw=1.57", "voxels": ["grass_block", "oak_log", "oak_leaves"], "status": {"health": 20, "food": 20, "saturation": 5, "oxygen": 315, "position": {"x": 5270.685021454552, "y": 73, "z": -4301.5}, "velocity": {"x": 0, "y": -0.0784000015258789, "z": 0}, "yaw": 1.9539925233402755e-13, "pitch": 0, "onGround": true, "equipment": [null, null, null, null, null, null], "name": "bot", "isInWater": false, "isInLava": false, "isCollidedHorizontally": false, "isCollidedVertically": true, "biome": "forest", "entities": {"cat": 24.047127920133335}, "timeOfDay": "day", "inventoryUsed": 1, "elapsedTime": 50}, "inventory": {"oak_log": 20}, "nearbyChests": {}, "blockRecords": ["dirt", "grass_block", "birch_log", "grass", "birch_leaves", "stone", "sand", "oak_log", "oak_leaves", "oak_planks", "crafting_table"]}], ["onChat", {"onChat": "pic3:{oak_leaves,18.75,oak_leaves,23.64,oak_leaves,23.03,oak_leaves,19.16,oak_leaves,18.28,oak_leaves,18.30,oak_leaves,19.56,oak_leaves,17.77,oak_log,8.87,oak_leaves,17.80,oak_log,8.91,oak_leaves,7.96,oak_leaves,7.21,oak_leaves,7.00,oak_leaves,7.14,oak_leaves,7.41,oak_leaves,7.34,oak_leaves,7.34,oak_leaves,7.48,oak_leaves,7.74,oak_leaves,8.12,oak_leaves,8.60,oak_leaves,9.16,grass_block,5.71,grass_block,5.71,grass_block,5.88,grass,5.79,oak_leaves,6.75,oak_leaves,7.32,oak_leaves,6.97,oak_leaves,7.52,oak_leaves,9.14,oak_leaves,8.26,oak_leaves,8.56,oak_log,9.26,oak_log,9.32,oak_leaves,7.73,oak_leaves,8.05,oak_leaves,7.31,oak_leaves,7.65,grass_block,2.02,grass_block,2.02,grass_block,2.47,grass_block,1.31,grass_block,1.31,grass_block,1.93,oak_log,2.59,oak_log,2.78,oak_log,3.27,grass_block,1.83,crafting_table,0.59,grass_block,2.23,grass,4.69,oak_log,5.97,oak_log,5.34,oak_log,5.43,oak_log,9.79,oak_log,12.79},yaw=3.14", "voxels": ["grass_block", "oak_leaves", "grass"], "status": {"health": 20, "food": 20, "saturation": 5, "oxygen": 313, "position": {"x": 5270.685021454552, "y": 73, "z": -4301.5}, "velocity": {"x": 0, "y": -0.0784000015258789, "z": 0}, "yaw": 1.5707963267949943, "pitch": 0, "onGround": true, "equipment": [null, null, null, null, null, null], "name": "bot", "isInWater": false, "isInLava": false, "isCollidedHorizontally": false, "isCollidedVertically": true, "biome": "forest", "entities": {"cat": 23.404425578427638}, "timeOfDay": "day", "inventoryUsed": 1, "elapsedTime": 80}, "inventory": {"oak_log": 20}, "nearbyChests": {}, "blockRecords": ["dirt", "grass_block", "birch_log", "grass", "birch_leaves", "stone", "sand", "oak_log", "oak_leaves", "oak_planks", "crafting_table"]}], ["onChat", {"onChat": "pic4:{grass_block,2.78,grass_block,1.93,grass_block,1.31,grass_block,1.31,grass_block,1.93,grass_block,16.51,oak_log,2.59,oak_log,2.78,oak_log,3.27,birch_leaves,12.87,grass_block,2.71,grass_block,1.83,birch_log,14.50,crafting_table,0.59,birch_log,14.54,birch_log,14.64,birch_leaves,12.86,oak_leaves,9.02,grass_block,3.00,grass_block,2.23,grass,4.69,oak_leaves,8.83,oak_leaves,8.18,grass,20.63,grass,16.66,oak_log,5.97,birch_leaves,9.98,birch_log,11.97,birch_log,12.01,birch_leaves,10.26,birch_leaves,10.50,oak_leaves,4.72,oak_leaves,20.97,birch_leaves,10.62,birch_leaves,10.86,oak_log,5.34,oak_log,5.43,oak_leaves,12.41,oak_leaves,12.61,oak_log,14.48,grass,11.99,oak_log,9.79,oak_log,14.52,oak_leaves,12.95,oak_leaves,13.14,grass,13.39,oak_leaves,9.97,oak_leaves,9.45,oak_leaves,9.02,oak_leaves,8.68,oak_leaves,10.02,oak_leaves,9.51,oak_leaves,9.08,oak_leaves,8.74,oak_leaves,8.51,oak_leaves,13.54,oak_leaves,13.73,oak_leaves,9.43,oak_leaves,13.34,oak_leaves,13.45,oak_leaves,12.77,birch_leaves,12.13,birch_leaves,11.53,birch_leaves,11.00,oak_leaves,10.15,oak_leaves,9.64,birch_leaves,12.33,birch_leaves,11.75,birch_leaves,11.23,birch_leaves,10.77,oak_log,12.79,oak_leaves,13.40,oak_leaves,10.80,oak_leaves,15.02,oak_leaves,14.34,oak_log,15.44,grass,19.80,grass,25.00,grass,24.02,oak_log,22.51},yaw=4.71", "voxels": ["grass_block", "oak_log"], "status": {"health": 20, "food": 20, "saturation": 5, "oxygen": 311, "position": {"x": 5270.685021454552, "y": 73, "z": -4301.5}, "velocity": {"x": 0, "y": -0.0784000015258789, "z": 0}, "yaw": 3.141592653589793, "pitch": 0, "onGround": true, "equipment": [null, null, null, null, null, null], "name": "bot", "isInWater": false, "isInLava": false, "isCollidedHorizontally": false, "isCollidedVertically": true, "biome": "forest", "entities": {"cat": 23.404425578427638}, "timeOfDay": "day", "inventoryUsed": 1, "elapsedTime": 110}, "inventory": {"oak_log": 20}, "nearbyChests": {}, "blockRecords": ["dirt", "grass_block", "birch_log", "grass", "birch_leaves", "stone", "sand", "oak_log", "oak_leaves", "oak_planks", "crafting_table"]}], ["observe", {"voxels": ["grass_block", "crafting_table", "oak_log"], "status": {"health": 20, "food": 20, "saturation": 5, "oxygen": 307, "position": {"x": 5270.685021454552, "y": 73, "z": -4301.5}, "velocity": {"x": 0, "y": -0.0784000015258789, "z": 0}, "yaw": 4.712388980384592, "pitch": 0, "onGround": true, "equipment": [null, null, null, null, null, null], "name": "bot", "isInWater": false, "isInLava": false, "isCollidedHorizontally": false, "isCollidedVertically": true, "biome": "forest", "entities": {"cat": 23.404425578427638}, "timeOfDay": "day", "inventoryUsed": 1, "elapsedTime": 160}, "inventory": {"oak_log": 20}, "nearbyChests": {}, "blockRecords": ["dirt", "grass_block", "birch_log", "grass", "birch_leaves", "stone", "sand", "oak_log", "oak_leaves", "oak_planks", "crafting_table"]}]]