{
    "response": {
        "explain": " Since this is the initial request, there's no prior code to explain or evaluate. The task is to mine 4 sand blocks in Minecraft using Mineflayer. I can find a sand block in pic1 at the direction yaw=0.00, and the distances are 7.04.",
        "subtask": "\n1) Perceive and teleport near the sand block.\n2) Mine a sand block.\n3) ...\n...\n",
        "code": "async function mineSand(bot) {\n\t// Subtask 1: Perceive and teleport near the sand block\n\tawait teleport(0.00, 7.04);\n}\n",
        "exec_code": "await mineSand(bot);"
    }
}