[["onChat", {"onChat": "pic1:{coarse_dirt,23.37,grass,22.54,fern,22.18,coarse_dirt,22.96,fern,20.91,coarse_dirt,25.27,coarse_dirt,22.64,spruce_log,20.70,fern,20.31,spruce_log,23.28,spruce_leaves,20.38,spruce_log,23.38,coarse_dirt,22.41,grass,21.26,fern,20.73,dead_bush,19.39,mossy_cobblestone,24.40,spruce_leaves,19.87,mossy_cobblestone,24.50,spruce_leaves,19.23,fern,18.90,large_fern,23.78,spruce_leaves,19.58,spruce_leaves,19.11,spruce_leaves,18.69,spruce_log,20.85,fern,20.22,large_fern,19.61,large_fern,18.51,grass,17.56,fern,17.16,poppy,16.50,large_fern,21.58,spruce_log,20.92,large_fern,19.69,large_fern,18.59,spruce_log,21.04,large_fern,17.14,grass,16.67,fern,15.86,fern,15.55,large_fern,20.17,large_fern,17.23,poppy,18.03,large_fern,15.78,dead_bush,15.33,fern,14.59,large_fern,15.88,mossy_cobblestone,17.96,grass,17.28,fern,16.63,large_fern,15.44,large_fern,14.91,poppy,14.01,mossy_cobblestone,18.75,large_fern,15.54,large_fern,15.01,mossy_cobblestone,23.71,mossy_cobblestone,18.00,large_fern,17.26,fern,15.23,large_fern,14.62,large_fern,13.55,grass,13.10,large_fern,17.35,large_fern,14.72,large_fern,13.66,podzol,11.13,mossy_cobblestone,23.23,fern,21.48,fern,20.63,large_fern,16.59,fern,15.85,large_fern,13.23,large_fern,12.69,spruce_log,11.17,mossy_cobblestone,23.29,large_fern,16.68,large_fern,13.34,large_fern,12.81,spruce_log,11.31,spruce_leaves,11.79,spruce_leaves,11.35,mossy_cobblestone,22.78,fern,21.88,large_fern,19.25,large_fern,14.44,poppy,13.73,grass,13.05,large_fern,19.33,large_fern,14.54,spruce_leaves,10.59,grass,21.45,grass,20.55,fern,18.76,large_fern,13.78,grass,13.03,dandelion,11.65,grass,10.47,large_fern,13.89,large_fern,15.66,large_fern,11.62,grass,10.91,large_fern,15.76,large_fern,11.75,spruce_leaves,19.43,spruce_log,20.71,large_fern,15.18,large_fern,14.30,spruce_log,11.76,large_fern,10.97,grass,8.85,spruce_leaves,19.84,large_fern,15.28,large_fern,14.41,spruce_log,11.89,large_fern,11.11,spruce_leaves,10.60,podzol,8.04,fern,14.76,grass,12.95,fern,8.10,spruce_leaves,9.98,podzol,8.94,poppy,6.62,large_fern,18.20,spruce_leaves,10.25,podzol,11.20,grass,9.35,poppy,7.57,mossy_cobblestone,4.59,mossy_cobblestone,4.13,mossy_cobblestone,3.88,grass,12.18,dandelion,11.24,mossy_cobblestone,4.00,spruce_leaves,14.20,spruce_leaves,12.51,poppy,9.93,podzol,3.28,podzol,2.59,podzol,2.16,podzol,2.84,podzol,2.00,podzol,1.41,spruce_log,4.60,spruce_log,4.70,spruce_log,5.01,spruce_log,5.49,podzol,2.72,podzol,1.83,podzol,1.14,mossy_cobblestone,6.52,brown_mushroom,3.52,brown_mushroom,0.54,mossy_cobblestone,6.60,spruce_log,11.69,spruce_log,11.91,podzol,2.95,podzol,2.16,podzol,1.62,mossy_cobblestone,5.64,fern,3.71,fern,2.77,mossy_cobblestone,7.67,fern,3.32,brown_mushroom,2.64,brown_mushroom,2.22,mossy_cobblestone,6.36,fern,3.51,brown_mushroom,3.20,mossy_cobblestone,6.14,spruce_log,4.19,spruce_log,4.31,spruce_log,13.54,fern,5.74,spruce_log,13.58,spruce_leaves,18.37,spruce_log,13.69,spruce_log,13.87,spruce_leaves,7.49,spruce_leaves,6.93,fern,20.47,fern,7.64,fern,6.34,spruce_leaves,19.75,spruce_leaves,9.46,spruce_leaves,7.30,spruce_leaves,7.02,fern,21.73,fern,8.47,fern,7.59,spruce_log,9.33,spruce_log,8.89,spruce_log,9.38,spruce_log,8.94,spruce_leaves,18.53,spruce_log,9.54,spruce_log,9.11,fern,11.24,mossy_cobblestone,13.98,spruce_leaves,13.36,spruce_leaves,12.67,spruce_leaves,12.02,spruce_leaves,11.42,mossy_cobblestone,13.96,podzol,23.36,spruce_leaves,14.08,podzol,23.85,spruce_log,14.85,spruce_leaves,14.33,podzol,24.38,brown_mushroom,18.53,fern,19.51,spruce_log,22.36},yaw=0.00", "voxels": ["podzol", "brown_mushroom", "fern", "spruce_log", "grass"], "status": {"health": 20, "food": 20, "saturation": 5, "oxygen": 400, "position": {"x": 10747.839976200874, "y": 101, "z": -2194.4800759225436}, "velocity": {"x": 0, "y": -0.0784000015258789, "z": 0}, "yaw": 4.709770986506601, "pitch": 0, "onGround": true, "equipment": [null, null, null, null, null, null], "name": "bot", "isInWater": false, "isInLava": false, "isCollidedHorizontally": false, "isCollidedVertically": true, "biome": "old_growth_spruce_taiga", "entities": {}, "timeOfDay": "day", "inventoryUsed": 0, "elapsedTime": 20}, "inventory": {}, "nearbyChests": {"(10748, 89, -2203)": "Unknown"}, "blockRecords": ["dirt", "grass_block", "birch_log", "grass", "birch_leaves", "stone", "podzol", "coarse_dirt", "fern", "dead_bush", "spruce_log", "poppy", "large_fern", "mossy_cobblestone", "spruce_leaves", "dandelion", "brown_mushroom"]}], ["onChat", {"onChat": "pic2:{coarse_dirt,23.37,grass,22.54,fern,22.18,coarse_dirt,22.96,fern,20.91,coarse_dirt,25.27,coarse_dirt,22.64,spruce_log,20.70,fern,20.31,spruce_log,23.28,spruce_leaves,20.38,spruce_log,23.38,coarse_dirt,22.41,grass,21.26,fern,20.73,dead_bush,19.39,mossy_cobblestone,24.40,spruce_leaves,19.87,mossy_cobblestone,24.50,spruce_leaves,19.23,fern,18.90,large_fern,23.78,spruce_leaves,19.58,spruce_leaves,19.11,spruce_leaves,18.69,spruce_log,20.85,fern,20.22,large_fern,19.61,large_fern,18.51,grass,17.56,fern,17.16,poppy,16.50,large_fern,21.58,spruce_log,20.92,large_fern,19.69,large_fern,18.59,spruce_log,21.04,large_fern,17.14,grass,16.67,fern,15.86,fern,15.55,large_fern,20.17,large_fern,17.23,poppy,18.03,large_fern,15.78,dead_bush,15.33,fern,14.59,large_fern,15.88,mossy_cobblestone,17.96,grass,17.28,fern,16.63,large_fern,15.44,large_fern,14.91,poppy,14.01,mossy_cobblestone,18.75,large_fern,15.54,large_fern,15.01,mossy_cobblestone,23.71,mossy_cobblestone,18.00,large_fern,17.26,fern,15.23,large_fern,14.62,large_fern,13.55,grass,13.10,large_fern,17.35,large_fern,14.72,large_fern,13.66,podzol,11.13,mossy_cobblestone,23.23,fern,21.48,fern,20.63,large_fern,16.59,fern,15.85,large_fern,13.23,large_fern,12.69,spruce_log,11.17,mossy_cobblestone,23.29,large_fern,16.68,large_fern,13.34,large_fern,12.81,spruce_log,11.31,spruce_leaves,11.79,spruce_leaves,11.35,mossy_cobblestone,22.78,fern,21.88,large_fern,19.25,large_fern,14.44,poppy,13.73,grass,13.05,large_fern,19.33,large_fern,14.54,spruce_leaves,10.59,grass,21.45,grass,20.55,fern,18.76,large_fern,13.78,grass,13.03,dandelion,11.65,grass,10.47,large_fern,13.89,large_fern,15.66,large_fern,11.62,grass,10.91,large_fern,15.76,large_fern,11.75,spruce_leaves,19.43,spruce_log,20.71,large_fern,15.18,large_fern,14.30,spruce_log,11.76,large_fern,10.97,grass,8.85,spruce_leaves,19.84,large_fern,15.28,large_fern,14.41,spruce_log,11.89,large_fern,11.11,spruce_leaves,10.60,podzol,8.04,fern,14.76,grass,12.95,fern,8.10,spruce_leaves,9.98,spruce_leaves,8.55,podzol,8.94,poppy,6.62,large_fern,18.20,spruce_leaves,10.25,spruce_leaves,8.63,podzol,11.20,grass,9.35,poppy,7.57,mossy_cobblestone,4.59,mossy_cobblestone,4.13,mossy_cobblestone,3.88,grass,12.18,dandelion,11.24,mossy_cobblestone,4.00,spruce_leaves,14.20,spruce_leaves,12.51,podzol,3.78,podzol,4.27,podzol,3.05,fern,3.90,fern,5.40,poppy,9.93,spruce_log,2.88,spruce_log,3.05,spruce_log,3.51,spruce_log,4.16,podzol,2.76,podzol,3.09,podzol,3.68,podzol,3.28,podzol,2.59,podzol,2.16,fern,2.15,fern,2.56,spruce_leaves,2.56,spruce_leaves,3.82,podzol,2.22,podzol,2.63,podzol,3.29,podzol,2.84,podzol,2.00,podzol,1.41,spruce_log,3.72,spruce_log,4.60,spruce_log,4.70,spruce_leaves,1.97,spruce_log,5.01,spruce_leaves,3.29,spruce_log,5.49,spruce_leaves,3.45},yaw=1.57", "voxels": ["podzol", "spruce_log"], "status": {"health": 20, "food": 20, "saturation": 5, "oxygen": 400, "position": {"x": 10747.839976200874, "y": 101, "z": -2194.4800759225436}, "velocity": {"x": 0, "y": -0.0784000015258789, "z": 0}, "yaw": 1.9539925233402755e-13, "pitch": 0, "onGround": true, "equipment": [null, null, null, null, null, null], "name": "bot", "isInWater": false, "isInLava": false, "isCollidedHorizontally": false, "isCollidedVertically": true, "biome": "old_growth_spruce_taiga", "entities": {}, "timeOfDay": "day", "inventoryUsed": 0, "elapsedTime": 50}, "inventory": {}, "nearbyChests": {"(10748, 89, -2203)": "Unknown"}, "blockRecords": ["dirt", "grass_block", "birch_log", "grass", "birch_leaves", "stone", "podzol", "coarse_dirt", "fern", "dead_bush", "spruce_log", "poppy", "large_fern", "mossy_cobblestone", "spruce_leaves", "dandelion", "brown_mushroom"]}], ["onChat", {"onChat": "pic3:{spruce_leaves,8.55,spruce_leaves,8.63,mossy_cobblestone,3.88,mossy_cobblestone,4.00,podzol,3.78,podzol,4.27,podzol,3.05,fern,3.90,fern,5.40,spruce_log,2.88,spruce_log,3.05,spruce_log,3.51,spruce_log,4.16,podzol,2.76,podzol,3.09,podzol,3.68,podzol,2.16,fern,2.15,fern,2.56,spruce_leaves,2.56,spruce_leaves,3.82,podzol,2.22,podzol,2.63,podzol,3.29,podzol,1.41,spruce_log,3.72,spruce_leaves,1.97,spruce_leaves,3.29,spruce_leaves,3.45,podzol,2.06,podzol,2.49,podzol,3.19,podzol,1.14,fern,1.79,large_fern,2.68,brown_mushroom,0.54,spruce_leaves,1.79,podzol,2.36,podzol,2.75,podzol,3.39,podzol,1.62,podzol,2.98,podzol,3.29,podzol,3.85,fern,2.43,fern,2.80,large_fern,4.22,brown_mushroom,2.22,fern,3.35,brown_mushroom,3.20,spruce_log,4.19,spruce_log,4.31,podzol,6.64,grass,6.26,podzol,8.76,spruce_leaves,11.77,spruce_log,11.48,spruce_log,11.73,fern,12.29,fern,15.43,fern,16.78,mossy_cobblestone,17.17,mossy_cobblestone,17.63,mossy_cobblestone,18.13,spruce_log,16.61,mossy_cobblestone,17.49},yaw=3.14", "voxels": ["mossy_cobblestone", "podzol", "spruce_log", "fern"], "status": {"health": 20, "food": 20, "saturation": 5, "oxygen": 400, "position": {"x": 10747.839976200874, "y": 101, "z": -2194.4800759225436}, "velocity": {"x": 0, "y": -0.0784000015258789, "z": 0}, "yaw": 1.5707963267949943, "pitch": 0, "onGround": true, "equipment": [null, null, null, null, null, null], "name": "bot", "isInWater": false, "isInLava": false, "isCollidedHorizontally": false, "isCollidedVertically": true, "biome": "old_growth_spruce_taiga", "entities": {}, "timeOfDay": "day", "inventoryUsed": 0, "elapsedTime": 80}, "inventory": {}, "nearbyChests": {"(10748, 89, -2203)": "Unknown"}, "blockRecords": ["dirt", "grass_block", "birch_log", "grass", "birch_leaves", "stone", "podzol", "coarse_dirt", "fern", "dead_bush", "spruce_log", "poppy", "large_fern", "mossy_cobblestone", "spruce_leaves", "dandelion", "brown_mushroom"]}], ["onChat", {"onChat": "pic4:{podzol,2.22,podzol,2.63,podzol,3.29,podzol,2.84,podzol,2.00,podzol,1.41,spruce_log,3.72,spruce_log,4.60,spruce_log,4.70,spruce_leaves,1.97,spruce_log,5.01,spruce_leaves,3.29,spruce_log,5.49,spruce_leaves,3.45,podzol,2.06,podzol,2.49,podzol,3.19,podzol,2.72,podzol,1.83,podzol,1.14,fern,1.79,large_fern,2.68,mossy_cobblestone,6.52,brown_mushroom,3.52,brown_mushroom,0.54,mossy_cobblestone,6.60,spruce_leaves,1.79,spruce_log,11.69,spruce_log,11.91,podzol,2.36,podzol,2.75,podzol,3.39,podzol,2.95,podzol,2.16,podzol,1.62,mossy_cobblestone,5.64,fern,3.71,fern,2.77,mossy_cobblestone,7.67,podzol,2.98,podzol,3.29,podzol,3.85,fern,2.43,fern,2.80,large_fern,4.22,fern,3.32,brown_mushroom,2.64,brown_mushroom,2.22,fern,3.35,mossy_cobblestone,6.36,fern,3.51,brown_mushroom,3.20,mossy_cobblestone,6.14,spruce_log,4.19,spruce_log,4.31,spruce_log,13.54,fern,5.74,spruce_log,13.58,spruce_leaves,18.37,spruce_log,13.69,spruce_log,13.87,spruce_leaves,7.49,spruce_leaves,6.93,podzol,6.64,grass,6.26,fern,20.47,fern,7.64,fern,6.34,spruce_leaves,19.75,spruce_leaves,9.46,spruce_leaves,7.30,spruce_leaves,7.02,fern,21.73,fern,8.47,fern,7.59,podzol,8.76,spruce_log,9.33,spruce_log,8.89,spruce_leaves,11.77,spruce_log,9.38,spruce_log,8.94,spruce_leaves,18.53,spruce_log,9.54,spruce_log,9.11,fern,11.24,mossy_cobblestone,13.98,spruce_leaves,13.36,spruce_leaves,12.67,spruce_leaves,12.02,spruce_leaves,11.42,mossy_cobblestone,13.96,spruce_log,11.48,spruce_log,11.73,podzol,23.36,spruce_leaves,14.08,fern,12.29,podzol,23.85,spruce_log,14.85,spruce_leaves,14.33,fern,15.43,podzol,24.38,fern,16.78,mossy_cobblestone,17.17,mossy_cobblestone,17.63,mossy_cobblestone,18.13,spruce_log,16.61,mossy_cobblestone,17.49,brown_mushroom,18.53,fern,19.51,spruce_log,22.36},yaw=4.71", "voxels": ["podzol", "spruce_log", "spruce_leaves"], "status": {"health": 20, "food": 20, "saturation": 5, "oxygen": 20, "position": {"x": 10747.839976200874, "y": 101, "z": -2194.4800759225436}, "velocity": {"x": 0, "y": -0.0784000015258789, "z": 0}, "yaw": 3.141592653589793, "pitch": 0, "onGround": true, "equipment": [null, null, null, null, null, null], "name": "bot", "isInWater": false, "isInLava": false, "isCollidedHorizontally": false, "isCollidedVertically": true, "biome": "old_growth_spruce_taiga", "entities": {}, "timeOfDay": "day", "inventoryUsed": 0, "elapsedTime": 110}, "inventory": {}, "nearbyChests": {"(10748, 89, -2203)": "Unknown"}, "blockRecords": ["dirt", "grass_block", "birch_log", "grass", "birch_leaves", "stone", "podzol", "coarse_dirt", "fern", "dead_bush", "spruce_log", "poppy", "large_fern", "mossy_cobblestone", "spruce_leaves", "dandelion", "brown_mushroom"]}], ["observe", {"voxels": ["podzol", "brown_mushroom", "fern", "spruce_log", "grass"], "status": {"health": 20, "food": 20, "saturation": 5, "oxygen": 400, "position": {"x": 10747.839976200874, "y": 101, "z": -2194.4800759225436}, "velocity": {"x": 0, "y": -0.0784000015258789, "z": 0}, "yaw": 4.712388980384592, "pitch": 0, "onGround": true, "equipment": [null, null, null, null, null, null], "name": "bot", "isInWater": false, "isInLava": false, "isCollidedHorizontally": false, "isCollidedVertically": true, "biome": "old_growth_spruce_taiga", "entities": {}, "timeOfDay": "day", "inventoryUsed": 0, "elapsedTime": 160}, "inventory": {}, "nearbyChests": {"(10748, 89, -2203)": "Unknown"}, "blockRecords": ["dirt", "grass_block", "birch_log", "grass", "birch_leaves", "stone", "podzol", "coarse_dirt", "fern", "dead_bush", "spruce_log", "poppy", "large_fern", "mossy_cobblestone", "spruce_leaves", "dandelion", "brown_mushroom"]}]]